pyees/__init__.py
pyees/fit.cp312-win_amd64.pyd
pyees/fit.py
pyees/profileFit.py
pyees/profilePyees.py
pyees/profileWindTunnelTest.py
pyees/prop.cp312-win_amd64.pyd
pyees/prop.py
pyees/sheet.cp312-win_amd64.pyd
pyees/sheet.py
pyees/solve.cp312-win_amd64.pyd
pyees/solve.py
pyees/testFit.py
pyees/testProp.py
pyees/testPyees.py
pyees/testSheet.py
pyees/testSolve.py
pyees/testUnit.py
pyees/testVariable.py
pyees/unit.cp312-win_amd64.pyd
pyees/unit.py
pyees/variable.cp312-win_amd64.pyd
pyees/variable.py
pyees-2.4.9.dist-info/licenses/LICENSE.txt
pyees-2.4.9.dist-info/METADATA
pyees-2.4.9.dist-info/WHEEL
pyees-2.4.9.dist-info/top_level.txt
pyees-2.4.9.dist-info/RECORD
