Metadata-Version: 2.4
Name: pyees
Version: 2.4.9
Summary: EES but for python. Pyees can be used do perform uncertanty (error) propagation. Furthermore, it can solve nonlinear systems of equations and look up material properties.
Home-page: https://github.com/jacobv95/pyees
Download-URL: https://github.com/jacobv95/pyees/archive/refs/tags/v1.0.tar.gz
Author: Jacob Vestergaard
Author-email: jacobvestergaard95@gmail.com
License: MIT
Keywords: python,data processing,uncertanty,EES
Classifier: Development Status :: 3 - Alpha
Classifier: Intended Audience :: Developers
Classifier: Topic :: Software Development :: Build Tools
Classifier: License :: OSI Approved :: MIT License
Classifier: Programming Language :: Python :: 3
Requires-Python: >=3.10
License-File: LICENSE.txt
Requires-Dist: numpy
Requires-Dist: scipy
Requires-Dist: openpyxl
Requires-Dist: xlrd
Requires-Dist: pyfluids
Requires-Dist: xlwt
Requires-Dist: plotly
Requires-Dist: matplotlib
Requires-Dist: python_calamine
Dynamic: author
Dynamic: author-email
Dynamic: classifier
Dynamic: download-url
Dynamic: home-page
Dynamic: keywords
Dynamic: license
Dynamic: license-file
Dynamic: requires-dist
Dynamic: requires-python
Dynamic: summary
